switchyard/__init__.py
switchyard/hostfirewall.py
switchyard/importcode.py
switchyard/llnetbase.py
switchyard/llnetreal.py
switchyard/llnetrealev.py
switchyard/llnettest.py
switchyard/outputfmt.py
switchyard/pcapffi.py
switchyard/swyard.py
switchyard/syinit.py
switchyard/textcolor.py
switchyard/lib/__init__.py
switchyard/lib/debugging.py
switchyard/lib/exceptions.py
switchyard/lib/interface.py
switchyard/lib/logging.py
switchyard/lib/testing.py
switchyard/lib/userlib.py
switchyard/lib/address/__init__.py
switchyard/lib/openflow/__init__.py
switchyard/lib/openflow/ofswitch.py
switchyard/lib/openflow/openflow10.py
switchyard/lib/openflow/openflow13.py
switchyard/lib/packet/__init__.py
switchyard/lib/packet/arp.py
switchyard/lib/packet/common.py
switchyard/lib/packet/ethernet.py
switchyard/lib/packet/icmp.py
switchyard/lib/packet/icmpv6.py
switchyard/lib/packet/ipv4.py
switchyard/lib/packet/ipv6.py
switchyard/lib/packet/null.py
switchyard/lib/packet/packet.py
switchyard/lib/packet/ripv2.py
switchyard/lib/packet/tcp.py
switchyard/lib/packet/udp.py
switchyard/lib/packet/util.py
switchyard/lib/socket/__init__.py
switchyard/lib/socket/socketemu.py
switchyard/lib/topo/__init__.py
switchyard/lib/topo/topobuild.py
switchyard/lib/topo/util.py
switchyard/sim/__init__.py
switchyard/sim/cli.py
switchyard/sim/linkem.py
switchyard/sim/monitor.py
switchyard/sim/nodeexec.py
switchyard-1.0.0.dist-info/COPYING
switchyard-1.0.0.dist-info/METADATA
switchyard-1.0.0.dist-info/WHEEL
switchyard-1.0.0.dist-info/entry_points.txt
switchyard-1.0.0.dist-info/top_level.txt
switchyard-1.0.0.dist-info/zip-safe
switchyard-1.0.0.dist-info/RECORD
