Metadata-Version: 2.1
Name: switchyard
Version: 1.0.0
Summary: Switchyard is a framework for creating networked systems
Home-page: https://github.com/jsommers/switchyard
Author: Joel Sommers
Author-email: jsommers@colgate.edu
License: This work is licensed under a Creative Commons Attribution-NonCommercial-ShareAlike 4.0 International License.  http://creativecommons.org/licenses/by-nc-sa/4.0/
Keywords: education,networked systems
Platform: UNKNOWN
Classifier: Programming Language :: Python :: 3 :: Only
Classifier: Development Status :: 4 - Beta
Classifier: Topic :: Scientific/Engineering
Classifier: Topic :: Education
Classifier: Topic :: Software Development :: Libraries
Classifier: Topic :: System :: Networking
Classifier: Environment :: Console
Classifier: Intended Audience :: Education
Classifier: Intended Audience :: Science/Research
Classifier: License :: OSI Approved :: GNU General Public License v3 (GPLv3)
Requires-Python: >=3.6
Requires-Dist: cffi (>=1.14.0)
Requires-Dist: colorama (>=0.4.3)
Requires-Dist: networkx (>=2.4)
Requires-Dist: psutil (>=5.7.0)
